drf_generator/__init__.py
drf_generator/routers.py
drf_generator/serializers.py
drf_generator/settings.py
drf_generator/views.py
drf_generator-0.0.7.dist-info/LICENSE
drf_generator-0.0.7.dist-info/WHEEL
drf_generator-0.0.7.dist-info/METADATA
drf_generator-0.0.7.dist-info/RECORD
