Metadata-Version: 2.1
Name: drf_generator
Version: 0.0.7
Summary: Good bye boilerplates
Home-page: UNKNOWN
License: UNKNOWN
Author: Henock Tesfaye
Author-email: jupiter.jupiter1@gmail.com
Classifier: License :: OSI Approved :: MIT License
